{
  "alterations": {
    "className": "Alterations",
    "url": "/qnamaker/v4.0/alterations",
    "operations": {
      "replaceAlterations": {
        "name": "replaceAlterations",
        "method": "put",
        "methodAlias": "replace",
        "target": [
          "alterations"
        ],
        "command": "qnamaker replace alterations --in wordAlterations.json",
        "pathFragment": "",
        "description": "",
        "entityName": "wordAlterations",
        "entityType": "WordAlterationsDTO"
      },
      "downloadAlterations": {
        "name": "download alterations",
        "method": "get",
        "methodAlias": "list",
        "target": [
          "alterations"
        ],
        "command": "qnamaker list alterations",
        "pathFragment": "",
        "description": ""
      }
    }
  },
  "endpointkeys": {
    "className": "Endpointkeys",
    "url": "/qnamaker/v4.0/endpointkeys",
    "operations": {
      "getEndpointKeys": {
        "name": "getEndpointKeys",
        "method": "get",
        "methodAlias": "list",
        "target": [
          "endpointkeys"
        ],
        "command": "qnamaker list endpointkeys",
        "pathFragment": "",
        "description": ""
      },
      "refreshEndpointKeys": {
        "name": "refreshEndpointKeys",
        "method": "patch",
        "methodAlias": "refresh",
        "target": [
          "endpointkeys"
        ],
        "command": "qnamaker refresh endpointkeys --keyType <string>",
        "pathFragment": "",
        "params": [
          {
            "type": "string",
            "name": "keyType",
            "in": "path",
            "required": true,
            "x-nullable": false,
            "description": "type of Key"
          }
        ],
        "description": ""
      }
    }
  },
  "knowledgebases": {
    "className": "Knowledgebases",
    "url": "/qnamaker/v4.0/knowledgebases",
    "operations": {
      "getKnowledgebasesForUser": {
        "name": "getKnowledgebasesForUser",
        "method": "get",
        "methodAlias": "list",
        "target": [
          "kbs",
          "knowledgebases",
          "kb"
        ],
        "command": "qnamaker list kbs",
        "pathFragment": "",
        "description": ""
      },
      "replaceKnowledgebase": {
        "name": "replaceKnowledgebase",
        "method": "put",
        "methodAlias": "replace",
        "target": [
          "kb",
          "knowledgebase"
        ],
        "command": "qnamaker replace kb --in replaceKb.json --kbId <string>",
        "pathFragment": "",
        "params": [
          {
            "type": "string",
            "name": "kbId",
            "in": "path",
            "required": true,
            "x-nullable": false,
            "description": "Knowledgebase id"
          }
        ],
        "description": "",
        "entityName": "replaceKb",
        "entityType": "ReplaceKbDTO"
      },
      "publishKnowledgebase": {
        "name": "publishKnowledgebase",
        "method": "post",
        "methodAlias": "publish",
        "target": [
          "kb",
          "knowledgebase"
        ],
        "command": "qnamaker publish kb --kbId <string>",
        "pathFragment": "",
        "params": [
          {
            "type": "string",
            "name": "kbId",
            "in": "path",
            "required": true,
            "x-nullable": false,
            "description": "Knowledgebase id"
          }
        ],
        "description": ""
      },
      "deleteKnowledgebase": {
        "name": "deleteKnowledgebase",
        "method": "delete",
        "methodAlias": "delete",
        "target": [
          "kb",
          "knowledgebase"
        ],
        "command": "qnamaker delete kb --kbId <string>",
        "pathFragment": "",
        "params": [
          {
            "type": "string",
            "name": "kbId",
            "in": "path",
            "required": true,
            "x-nullable": false,
            "description": "Knowledgebase id."
          }
        ],
        "description": ""
      },
      "getKnowledgebaseDetails": {
        "name": "getKnowledgebaseDetails",
        "method": "get",
        "methodAlias": "get",
        "target": [
          "kb",
          "knowledgebase"
        ],
        "command": "qnamaker get kb --kbId <string>",
        "pathFragment": "",
        "params": [
          {
            "type": "string",
            "name": "kbId",
            "in": "path",
            "required": true,
            "x-nullable": false,
            "description": "Knowledgebase id."
          },
          {
            "type": "string",
            "name": "environment",
            "in": "path",
            "required": false,
            "x-nullable": false,
            "default": "prod",
            "description": "The environment [prod or test] default is prod"
          }
        ],
        "description": ""
      }
    }
  },
  "createasync": {
    "className": "Createasync",
    "url": "/qnamaker/v4.0/knowledgebases/createasync",
    "operations": {
      "createKnowledgebase": {
        "name": "createKnowledgebase",
        "method": "post",
        "methodAlias": "create",
        "target": [
          "kb",
          "knowledgebase"
        ],
        "command": "qnamaker create kb --in createKbPayload.json",
        "pathFragment": "",
        "description": "",
        "entityName": "createKbPayload",
        "entityType": "CreateKbDTO"
      }
    }
  },
  "UpdateAsync": {
    "className": "UpdateAsync",
    "url": "/qnamaker/v4.0/knowledgebases/{kbId}/UpdateAsync",
    "operations": {
      "updateKnowledgebase": {
        "name": "updateKnowledgebase",
        "method": "patch",
        "methodAlias": "update",
        "target": [
          "kb",
          "knowledgebase"
        ],
        "command": "qnamaker update kb --in updateKb.json --kbId <string>",
        "pathFragment": "",
        "params": [
          {
            "type": "string",
            "name": "kbId",
            "in": "path",
            "required": true,
            "x-nullable": false,
            "description": "Knowledgebase id"
          }
        ],
        "description": "",
        "entityName": "updateKb",
        "entityType": "UpdateKbOperationDTO"
      }
    }
  },
  "generateAnswer": {
    "className": "GenerateAnswer",
    "url": "/qnamaker/knowledgebases/{kbId}/generateAnswer",
    "operations": {
      "generateAnswer": {
        "name": "generateAnswer",
        "method": "post",
        "methodAlias": "query",
        "target": [],
        "command": "qnamaker query --question \"how do I turn it on\" --top 5",
        "pathFragment": "",
        "params": [
          {
            "name": "question",
            "in": "question",
            "description": "question you want to ask",
            "required": true,
            "type": "string"
          },
          {
            "name": "top",
            "in": "top",
            "description": "number of answers you would like",
            "required": false,
            "type": "number"
          },
          {
            "name": "knowledgeBaseID",
            "alias": "kbid",
            "in": "path",
            "description": "kbI, this should be get from QnAMaker portal",
            "required": false,
            "type": "string"
          }
        ],
        "description": "Returns the list of answers for the given question sorted in descending order of ranking score.",
        "entityName": "generateAnswer",
        "entityType": "GenerateAnswer"
      }
    }
  },
  "qna": {
    "className": "Qna",
    "url": "/qnamaker/v4.0/knowledgebases/{kbId}/{environment}/qna",
    "operations": {
      "downloadKnowledgebase": {
        "name": "downloadKnowledgebase",
        "method": "get",
        "methodAlias": "export",
        "target": [
          "kb",
          "knowledgebase"
        ],
        "command": "qnamaker export kb --kbId <string> --environment <string>",
        "pathFragment": "",
        "params": [
          {
            "type": "string",
            "name": "kbId",
            "in": "path",
            "required": true,
            "x-nullable": false,
            "description": "Knowledgebase id"
          },
          {
            "type": "string",
            "name": "environment",
            "in": "path",
            "required": true,
            "x-schema": {
              "$ref": "#/definitions/KnowledgebaseEnvironment"
            },
            "x-nullable": false,
            "description": "Specifies whether environment is Test or Prod.",
            "enum": [
              "Prod",
              "Test"
            ]
          }
        ],
        "description": ""
      }
    }
  },
  "operations": {
    "className": "Operations",
    "url": "/qnamaker/v4.0/operations/{operationId}",
    "operations": {
      "getOperationDetails": {
        "name": "getOperationDetails",
        "method": "get",
        "methodAlias": "get",
        "target": [
          "OperationDetails",
          "operationdetails"
        ],
        "command": "qnamaker get OperationDetails --operationId <string>",
        "pathFragment": "",
        "params": [
          {
            "type": "string",
            "name": "operationId",
            "in": "path",
            "required": true,
            "x-nullable": false,
            "description": "Operation id."
          }
        ],
        "description": ""
      }
    }
  }
}